plumitas/__init__.py
plumitas/core.py
plumitas/input.py
plumitas/version.py
plumitas/data/plumed_bin.dat
plumitas/data/plumed_bin_space.dat
plumitas/tests/__init__.py
plumitas/tests/test_plumitas.py
plumitas-0.0.1.dev3.dist-info/DESCRIPTION.rst
plumitas-0.0.1.dev3.dist-info/METADATA
plumitas-0.0.1.dev3.dist-info/RECORD
plumitas-0.0.1.dev3.dist-info/WHEEL
plumitas-0.0.1.dev3.dist-info/metadata.json
plumitas-0.0.1.dev3.dist-info/top_level.txt
