Metadata-Version: 2.0
Name: plumitas
Version: 0.0.1.dev3
Summary: plumitas: Pythonic analysis and visualization of Plumed output files
Home-page: http://github.com/UWPRG/plumitas
Author: Josh Smith
Author-email: jsmith07@uw.edu
License: MIT
Platform: OS Independent
Classifier: Development Status :: 3 - Alpha
Classifier: Environment :: Console
Classifier: Intended Audience :: Science/Research
Classifier: License :: OSI Approved :: MIT License
Classifier: Operating System :: OS Independent
Classifier: Programming Language :: Python :: 3.6
Classifier: Topic :: Scientific/Engineering
Requires: numpy
Requires-Python: ~=3.6
Requires-Dist: numpy
